gnome_hud-1.4.1.data/data/share/applications/gnomehud.desktop
gnomehud/__init__.py
gnomehud/appmenu.py
gnomehud/command.py
gnomehud/keybinder.py
gnomehud/handlers/__init__.py
gnomehud/handlers/default.py
gnomehud/handlers/rofi.py
gnomehud/utils/__init__.py
gnomehud/utils/bamf.py
gnomehud/utils/fuzzy.py
gnomehud/utils/menu.py
gnomehud/utils/service.py
gnomehud/utils/shell.py
gnome_hud-1.4.1.dist-info/LICENSE.txt
gnome_hud-1.4.1.dist-info/METADATA
gnome_hud-1.4.1.dist-info/WHEEL
gnome_hud-1.4.1.dist-info/entry_points.txt
gnome_hud-1.4.1.dist-info/top_level.txt
gnome_hud-1.4.1.dist-info/RECORD
