Metadata-Version: 2.1
Name: gnome-hud
Version: 1.4.1
Summary: Unity like HUD menu for the GNOME Desktop Environment
Home-page: https://github.com/hardpixel/gnome-hud
Author: Jonian Guveli
Author-email: jonian@hardpixel.eu
License: UNKNOWN
Project-URL: Bug Reports, https://github.com/hardpixel/gnome-hud/issues
Project-URL: Source, https://github.com/hardpixel/gnome-hud
Platform: UNKNOWN
Classifier: Programming Language :: Python :: 3
Classifier: License :: OSI Approved :: GNU General Public License v3 (GPLv3)
Classifier: Operating System :: POSIX :: Linux
Requires-Dist: PyGObject (>=3.30.0)
Requires-Dist: fuzzysearch (>=0.5.0)
